LICENSE
README.md
marcx.py
setup.py
marcx.egg-info/PKG-INFO
marcx.egg-info/SOURCES.txt
marcx.egg-info/dependency_links.txt
marcx.egg-info/requires.txt
marcx.egg-info/top_level.txt
tests/test_docdict.py
tests/test_esmarc.py
tests/test_misc.py
tests/test_record.py