Metadata-Version: 2.1
Name: marcx
Version: 0.3.0
Summary: MARC record manipulation library based on pymarc
Home-page: https://github.com/ubleipzig/marcx
Author: Martin Czygan
Author-email: martin.czygan@gmail.com
Classifier: Development Status :: 4 - Beta
Classifier: Intended Audience :: Education
Classifier: Intended Audience :: Developers
Classifier: Intended Audience :: Information Technology
Classifier: License :: OSI Approved :: GNU General Public License v3 (GPLv3)
Classifier: Programming Language :: Python :: 2
Classifier: Programming Language :: Python :: 3
Classifier: Topic :: Text Processing :: General
License-File: LICENSE
Requires-Dist: pymarc>=5.0
Requires-Dist: jsonpath-rw>=1.3.0
Requires-Dist: ply>=3.4
Requires-Dist: future>=0.16
